django_microservices_admin/__init__.py
django_microservices_admin/apps.py
django_microservices_admin/routers.py
django_microservices_admin/settings.py
django_microservices_admin/management/__init__.py
django_microservices_admin/management/commands/__init__.py
django_microservices_admin/management/commands/update_microservices_admin.py
django_microservices_admin/migrations/__init__.py
django_microservices_admin-0.0.1.dist-info/LICENSE
django_microservices_admin-0.0.1.dist-info/METADATA
django_microservices_admin-0.0.1.dist-info/WHEEL
django_microservices_admin-0.0.1.dist-info/top_level.txt
django_microservices_admin-0.0.1.dist-info/RECORD
