Metadata-Version: 2.1
Name: django-microservices-admin
Version: 0.0.1
Summary: Utilizing Django Admin to manage microservices data
Home-page: https://github.com/robotstech/django-microservices-admin
License: MIT
Keywords: Django,django-admin,microservices
Platform: UNKNOWN
Classifier: Development Status :: 1 - Planning
Classifier: Environment :: Web Environment
Classifier: Framework :: Django
Classifier: Framework :: Django :: 3.2
Classifier: Intended Audience :: Developers
Classifier: License :: OSI Approved :: MIT License
Classifier: License :: OSI Approved :: MIT No Attribution License (MIT-0)
Classifier: Operating System :: OS Independent
Classifier: Programming Language :: Python
Classifier: Programming Language :: Python :: 3
Classifier: Programming Language :: Python :: 3.8
Classifier: Programming Language :: Python :: 3 :: Only
Classifier: Topic :: Internet :: WWW/HTTP
License-File: LICENSE
Requires-Dist: django (>=3.2)
Requires-Dist: dj-database-url (>=0.5.0)
Provides-Extra: mysql
Requires-Dist: mysqlclient (>=2.1.0) ; extra == 'mysql'
Provides-Extra: postgres
Requires-Dist: psycopg2-binary (>=2.9.3) ; extra == 'postgres'
